pyams_auth_sql/__init__.py
pyams_auth_sql/include.py
pyams_auth_sql/interfaces.py
pyams_auth_sql/plugin.py
pyams_auth_sql/doctests/README.rst
pyams_auth_sql/locales/pyams_auth_sql.pot
pyams_auth_sql/locales/fr/LC_MESSAGES/pyams_auth_sql.mo
pyams_auth_sql/locales/fr/LC_MESSAGES/pyams_auth_sql.po
pyams_auth_sql/tests/__init__.py
pyams_auth_sql/tests/test_utilsdocs.py
pyams_auth_sql/tests/test_utilsdocstrings.py
pyams_auth_sql/zmi/__init__.py
pyams_auth_sql-2.0.1.dist-info/LICENSE
pyams_auth_sql-2.0.1.dist-info/METADATA
pyams_auth_sql-2.0.1.dist-info/WHEEL
pyams_auth_sql-2.0.1.dist-info/namespace_packages.txt
pyams_auth_sql-2.0.1.dist-info/top_level.txt
pyams_auth_sql-2.0.1.dist-info/RECORD
