Metadata-Version: 2.1
Name: pyams-auth-sql
Version: 2.0.1
Summary: PyAMS sql authentication
Home-page: https://pyams.readthedocs.io
Author: Thierry Florac
Author-email: tflorac@ulthar.net
License: ZPL
Keywords: Pyramid PyAMS
Classifier: License :: OSI Approved :: Zope Public License
Classifier: Development Status :: 4 - Beta
Classifier: Programming Language :: Python
Classifier: Framework :: Pyramid
Classifier: Topic :: Software Development :: Libraries :: Python Modules
License-File: LICENSE
Requires-Dist: setuptools
Requires-Dist: persistent
Requires-Dist: pyams-alchemy
Requires-Dist: pyams-security >=1.8.1
Requires-Dist: pyams-site
Requires-Dist: pyams-utils
Requires-Dist: pyramid >=2.0.0
Requires-Dist: sqlalchemy
Requires-Dist: zope.container
Requires-Dist: zope.password
Requires-Dist: zope.schema
Provides-Extra: test
Requires-Dist: pyams-security-views ; extra == 'test'
Requires-Dist: pyams-zmi ; extra == 'test'
Requires-Dist: pyramid-zcml ; extra == 'test'
Requires-Dist: zope.exceptions ; extra == 'test'
